ecgmentations/__init__.py
ecgmentations/__version__.py
ecgmentations/augmentations/__init__.py
ecgmentations/augmentations/enum.py
ecgmentations/augmentations/functional.py
ecgmentations/augmentations/misc.py
ecgmentations/augmentations/transformations.py
ecgmentations/augmentations/transforms.py
ecgmentations/augmentations/filter/__init__.py
ecgmentations/augmentations/filter/functional.py
ecgmentations/augmentations/filter/transformations.py
ecgmentations/augmentations/frequency_based/__init__.py
ecgmentations/augmentations/frequency_based/functional.py
ecgmentations/augmentations/frequency_based/transforms.py
ecgmentations/augmentations/pulse/__init__.py
ecgmentations/augmentations/pulse/functional.py
ecgmentations/augmentations/pulse/transformations.py
ecgmentations/augmentations/pulse/transforms.py
ecgmentations/augmentations/time/__init__.py
ecgmentations/augmentations/time/functional.py
ecgmentations/augmentations/time/transformations.py
ecgmentations/augmentations/time/transforms.py
ecgmentations/augmentations/time_based/__init__.py
ecgmentations/augmentations/time_based/functional.py
ecgmentations/augmentations/time_based/transforms.py
ecgmentations/core/__init__.py
ecgmentations/core/application.py
ecgmentations/core/augmentation.py
ecgmentations/core/composition.py
ecgmentations/core/compositions.py
ecgmentations/core/constants.py
ecgmentations/core/enum.py
ecgmentations/core/modification.py
ecgmentations/core/modifications.py
ecgmentations/core/transformation.py
ecgmentations/core/transforms.py
ecgmentations/core/utils.py
tests/ecgmentations/__init__.py
tests/ecgmentations/augmentations/__init__.py
tests/ecgmentations/augmentations/test_functional.py
tests/ecgmentations/augmentations/test_misc.py
tests/ecgmentations/augmentations/test_transformations.py
tests/ecgmentations/augmentations/test_transforms.py
tests/ecgmentations/augmentations/frequency_based/__init__.py
tests/ecgmentations/augmentations/frequency_based/test_functional.py
ecgmentations-0.0.9.dist-info/LICENSE
ecgmentations-0.0.9.dist-info/METADATA
ecgmentations-0.0.9.dist-info/WHEEL
ecgmentations-0.0.9.dist-info/top_level.txt
ecgmentations-0.0.9.dist-info/RECORD
