Metadata-Version: 2.1
Name: ecgmentations
Version: 0.0.9
Summary: Ecg augmentation library and easy to use wrapper around other libraries
Home-page: https://github.com/rostepifanov/ecgmentations
Author: Rostislav Epifanov
Author-email: rostepifanov@gmail.com
License: MIT
Classifier: Development Status :: 4 - Beta
Classifier: License :: OSI Approved :: MIT License
Classifier: Intended Audience :: Developers
Classifier: Intended Audience :: Science/Research
Classifier: Operating System :: OS Independent
Classifier: Programming Language :: Python
Classifier: Programming Language :: Python :: 3
Classifier: Programming Language :: Python :: 3.7
Classifier: Programming Language :: Python :: 3.8
Classifier: Programming Language :: Python :: 3.9
Classifier: Programming Language :: Python :: 3.10
Classifier: Programming Language :: Python :: 3.11
Classifier: Topic :: Scientific/Engineering
Classifier: Topic :: Scientific/Engineering :: Artificial Intelligence
Classifier: Topic :: Software Development
Classifier: Topic :: Software Development :: Libraries
Classifier: Topic :: Software Development :: Libraries :: Python Modules
Requires-Python: >=3.7
License-File: LICENSE
Requires-Dist: numpy >=1.20.0
Requires-Dist: scipy >=1.10.1
Requires-Dist: opencv-python-headless >=4.1.1
Provides-Extra: tests
Requires-Dist: pytest ; extra == 'tests'
